doggyscript/__init__.py
doggyscript-1.0.0.dist-info/LICENCE.txt
doggyscript-1.0.0.dist-info/METADATA
doggyscript-1.0.0.dist-info/WHEEL
doggyscript-1.0.0.dist-info/top_level.txt
doggyscript-1.0.0.dist-info/RECORD
