Metadata-Version: 2.1
Name: doggyscript
Version: 1.0.0
Summary: yay
Home-page: UNKNOWN
Author: dbcjdc sdjsdu
Author-email: itggpqjodjplsdrhmt@nthrl.com
License: MIT
Keywords: Assist mode
Platform: UNKNOWN
Classifier: Development Status :: 5 - Production/Stable
Classifier: Intended Audience :: Education
Classifier: Operating System :: Microsoft :: Windows :: Windows 10
Classifier: License :: OSI Approved :: MIT License
Classifier: Programming Language :: Python :: 3
License-File: LICENCE.txt
